LICENSE.txt
MANIFEST.in
README.rst
setup.cfg
setup.py
EcanDbParams.egg-info/PKG-INFO
EcanDbParams.egg-info/SOURCES.txt
EcanDbParams.egg-info/dependency_links.txt
EcanDbParams.egg-info/top_level.txt
ecandbparams/__init__.py
ecandbparams/sql_arg_class.py
ecandbparams/tests/__init__.py
ecandbparams/tests/test_sql_arg.py